README.rst
setup.cfg
setup.py
GraphAlViz.egg-info/PKG-INFO
GraphAlViz.egg-info/SOURCES.txt
GraphAlViz.egg-info/dependency_links.txt
GraphAlViz.egg-info/entry_points.txt
GraphAlViz.egg-info/pbr.json
GraphAlViz.egg-info/requires.txt
GraphAlViz.egg-info/top_level.txt
graphalviz/__init__.py
graphalviz/client.py
graphalviz/core.py
graphalviz/dfs_client.py
graphalviz/dfs_core.py
graphalviz/examples.py
graphalviz/graph_example.g
graphalviz/graphalviz.py
graphalviz/log.py
graphalviz/logging.json
graphalviz/server.py
graphalviz/settings.py
graphalviz/tools.py