Metadata-Version: 1.1
Name: GraphAlViz
Version: 0.5.0
Summary: Graph algorithm visualization library
Home-page: https://bitbucket.org/waldekmalec/graf/
Author: Waldemar Malec
Author-email: waldekmalec@gmail.com
License: MIT
Keywords: graph,visualization
Platform: UNKNOWN
Classifier: Development Status :: 3 - Alpha
Classifier: Intended Audience :: Developers
Classifier: Topic :: Software Development :: Build Tools
Classifier: License :: OSI Approved :: MIT License
Classifier: Programming Language :: Python :: 2
Classifier: Programming Language :: Python :: 2.7
Classifier: Programming Language :: Python :: 3
Classifier: Programming Language :: Python :: 3.4
